simplere/__init__.py
simplere/core.py
simplere-1.2.13.dist-info/DESCRIPTION.rst
simplere-1.2.13.dist-info/METADATA
simplere-1.2.13.dist-info/RECORD
simplere-1.2.13.dist-info/WHEEL
simplere-1.2.13.dist-info/metadata.json
simplere-1.2.13.dist-info/top_level.txt
